EasyImgConverter/__init__.py
EasyImgConverter/main.py
EasyImgConverter/data_test/cat.jpeg
EasyImgConverter-0.1.dist-info/DESCRIPTION.rst
EasyImgConverter-0.1.dist-info/METADATA
EasyImgConverter-0.1.dist-info/RECORD
EasyImgConverter-0.1.dist-info/WHEEL
EasyImgConverter-0.1.dist-info/entry_points.txt
EasyImgConverter-0.1.dist-info/metadata.json
EasyImgConverter-0.1.dist-info/top_level.txt
