Metadata-Version: 2.0
Name: EasyImgConverter
Version: 0.1
Summary: Python tool for easy and quick conversion of images between different formats.
Home-page: https://github.com/alzaia/easy_img_converter
Author: Aldo Zaimi
Author-email: zaimialdo@gmail.com
License: MIT
Platform: UNKNOWN
Classifier: Development Status :: 3 - Alpha
Classifier: License :: OSI Approved :: MIT License
Classifier: Programming Language :: Python :: 2.7
Requires-Dist: numpy (>=1.12.0)
Requires-Dist: imageio (>=2.2.0)
